pysapgui/__init__.py
pysapgui/alv_grid.py
pysapgui/sapexistedsession.py
pysapgui/sapgui.py
pysapgui/sapguielements.py
pysapgui/saplogonexe.py
pysapgui/saplogonini.py
pysapgui/saplogonpwd.py
pysapgui/sapnewsession.py
pysapgui/software_components.py
pysapgui/transaction.py
pysapgui/transaction_se16.py
PySapGUI-1.0.7.dist-info/LICENSE
PySapGUI-1.0.7.dist-info/METADATA
PySapGUI-1.0.7.dist-info/WHEEL
PySapGUI-1.0.7.dist-info/top_level.txt
PySapGUI-1.0.7.dist-info/RECORD
