Metadata-Version: 2.1
Name: PySapGUI
Version: 1.0.7
Summary: SAP GUI Scripting Library in Python
Home-page: https://github.com/gutskodv/PySapGUI
Author: Dmitry Gutsko
Author-email: gutskodv@gmail.com
License: GPL v2
License-File: LICENSE
Requires-Dist: pywin32 (>=227)
